CHANGELOG.rst
MANIFEST.in
README.rst
cryptosyspki.py
pyproject.toml
cryptosyspki.egg-info/PKG-INFO
cryptosyspki.egg-info/SOURCES.txt
cryptosyspki.egg-info/dependency_links.txt
cryptosyspki.egg-info/top_level.txt
test/pkiPythonTestFiles.zip
test/test_pki.py
test/work/4.2.bin
test/work/AlicePrivRSASign.p8e
test/work/AlicePubRSA.pub
test/work/AliceRSASignByCarl.cer
test/work/BobPrivRSAEncrypt.p8e
test/work/BobRSASignByCarl.cer
test/work/CarlPrivRSASign.p8e
test/work/CarlRSASelf.cer
test/work/Ed25519-ietf-selfsigned.cer
test/work/Ed448-selfsigned.cer
test/work/File with a long name and spaces hello there all good yes thanks.txt
test/work/UTNUSERFirst-Object.cer
test/work/X448-alice-self-issued.cer
test/work/X448-alice-self.p8
test/work/alice.pfx
test/work/bob-lamps.crt
test/work/bob-lamps.p12
test/work/bob-lamps.p8
test/work/bob.p7b
test/work/dims.cer
test/work/ecprivkey.p8
test/work/edkey448.p8
test/work/edwards-ietf-ex.p8
test/work/edwards-ietf.p8
test/work/excontent.txt
test/work/lamps-alice.decrypt.p8.pem
test/work/lamps-alice.encrypt.crt
test/work/lamps-alice.p8
test/work/lamps-bob.crt
test/work/lamps-bob.p8
test/work/lamps-ca.ed25519.crt
test/work/lamps-ca.ed25519.p8
test/work/lamps-carlos.decrypt.p8
test/work/lamps-carlos.encrypt.cer
test/work/lamps-dana.decrypt.p8.pem
test/work/lamps-dana.encrypt.crt
test/work/maria-mx.cer
test/work/ocsp_response_ok_dims.dat
test/work/rfc3280bis_CRL.crl
test/work/rfc3280bis_cert1.cer
test/work/rfc3280bis_cert2.cer
test/work/rsa-oaep-1.p8
test/work/rsa-oaep-1.pub
test/work/sifen-emisor.cer
test/work/sifen-emisor.p8e
test/work/smallca.cer
test/work/sonnets.txt
test/work/test-daiwei.xml
test/work/test-iso88591.xml
test/work/test-utf8.xml
test/work/你好.txt