Metadata-Version: 2.1
Name: cryptosyspki
Version: 22.1.0.post1
Summary: Python interface to CryptoSys PKI
Author: David Ireland, DI Management Services Pty Ltd
Project-URL: Homepage, https://www.cryptosys.net/pki/
Project-URL: Issues, https://www.cryptosys.net/contact/
Classifier: Programming Language :: Python :: 3
Requires-Python: >=3.6
